genochain/__init__.py
genochain/genochain.py
genochain-0.0.7.dist-info/METADATA
genochain-0.0.7.dist-info/WHEEL
genochain-0.0.7.dist-info/top_level.txt
genochain-0.0.7.dist-info/RECORD
