Metadata-Version: 2.1
Name: genochain
Version: 0.0.7
Summary: Storing and versioning genomics data on a blockchain
Author: GenoChain(Sanjana Sharma)
Author-email: <sharmasanjana1947@gmail.com>
Keywords: python,blockchain,genomics,fasta,block,biology
Classifier: Development Status :: 1 - Planning
Classifier: Intended Audience :: Developers
Classifier: Programming Language :: Python :: 3
Classifier: Operating System :: Unix
Classifier: Operating System :: MacOS :: MacOS X
Classifier: Operating System :: Microsoft :: Windows
